mosaic/__init__.py
mosaic/constants.py
mosaic/participantinfo.py
mosaic/stiminfo.py
mosaic/datasets/__init__.py
mosaic/datasets/merged.py
mosaic/datasets/single_subject.py
mosaic/datasets/resting_state/__init__.py
mosaic/datasets/resting_state/bold_moments.py
mosaic/datasets/resting_state/nsd.py
mosaic/datasets/resting_state/things_fmri.py
mosaic/datasets/timeseries/__init__.py
mosaic/models/__init__.py
mosaic/models/architectures.py
mosaic/models/pretrained.py
mosaic/models/readout.py
mosaic/models/transforms.py
mosaic/utils/__init__.py
mosaic/utils/aws.py
mosaic/utils/checkpoint_conversion.py
mosaic/utils/download.py
mosaic/utils/folder.py
mosaic/utils/inference.py
mosaic/utils/json.py
mosaic/utils/merging.py
mosaic/utils/parcellation.py
mosaic/utils/visualization.py
mosaic_dataset-0.0.6.dist-info/METADATA
mosaic_dataset-0.0.6.dist-info/WHEEL
mosaic_dataset-0.0.6.dist-info/top_level.txt
mosaic_dataset-0.0.6.dist-info/RECORD
