Metadata-Version: 2.1
Name: mosaic-dataset
Version: 0.0.6
Summary: A scalable framework for fMRI dataset aggregation and modeling of human vision
Home-page: https://github.com/murtylab/mosaic-dataset
Author: Benjamin Lahner, Mayukh Deb, N. Apurva Ratan Murty, Aude Oliva
Author-email: blahner@mit.edu; mayukh@gatech.edu; ratan@gatech.edu; oliva@mit.edu
Classifier: Programming Language :: Python :: 3
Classifier: Operating System :: OS Independent
Requires-Dist: hcp-utils
Requires-Dist: numpy
Requires-Dist: h5py
Requires-Dist: nilearn
Requires-Dist: torch
Requires-Dist: matplotlib
Requires-Dist: tqdm
Requires-Dist: torchvision
Requires-Dist: ipython
